{
  "_id": 6,
  "id": "crow",
  "name": "Кроу",
  "suitName": "Фанатичное преследование",
  "hash": "SSR11",
  "rarity": "SSR",
  "bonus": [
    {
      "count": 2,
      "value": "Увеличивает крит. урон по целям с менее чем 60% ОЗ на 33%/42%/50%/58%."
    },
    {
      "count": 4,
      "value": "Крит. удары каждую секунду наносят доп. постепенный урон в размере 12%/15%/18%/21% от АТК в течение 5 сек. Этот эффект не накапливается."
    }
  ],
  "mind": {
    "name": "Одиннадцатое измерение",
    "desc": "Некоторые вещи неосязаемы, но они действительно существуют."
  },
  "memory": {
    "name": "Эффект янтаря",
    "desc": "Прошлое осталось в прошлом. Настоящее — вот о чем нужно заботиться."
  },
  "belief": {
    "name": "Отчаянное выживание",
    "desc": "Никогда не сдавайтесь, даже если кажется, что шансов никаких."
  },
  "emotion": {
    "name": "Свое видение",
    "desc": "Причудливое клоунское представление, иногда очень сложное для понимания."
  }
}